cluswasser/__init__.py
cluswasser/cluster.py
cluswasser/cluster_wasser.py
cluswasser/color_mapping.py
cluswasser/tree.py
cluswasser/union_find.py
cluswasser/models/__init__.py
cluswasser/models/cluster.py
cluswasser/models/edge.py
cluswasser/models/range.py
cluswasser/models/vertex.py
cluster_wasser-1.0.0.dist-info/LICENSE
cluster_wasser-1.0.0.dist-info/METADATA
cluster_wasser-1.0.0.dist-info/WHEEL
cluster_wasser-1.0.0.dist-info/top_level.txt
cluster_wasser-1.0.0.dist-info/RECORD
